{
	"id": "2020-03_ev_charging",
	"title": "Recharge de véhicules électriques",
	"start_date": "2020-03-01",
	"end_date": "2020-03-31",
	"summary": "Au moins 10 000 bornes de recharge seraient installées en France alors que seules 4 500 environ seraient décrites dans notre base de données. L'objectif du projet est de se rapprocher autant que faire se peut de la quantité disponible sur le terrain.",
	"datasources": [
		{ "source": "osmose", "item": "8411", "country": "france*", "name": "Borne à compléter", "color": "green" },
		{ "source": "osmose", "item": "8410", "country": "france*", "name": "Borne à importer", "color": "red" }
	],
	"editors": {
		"all": {
			"comment": "Intégration bornes de recharge véhicules électriques",
			"hashtags": "balancetaborne"
		},
		"iD": {
			"background": "fr.ign.bdortho"
		}
	}
}
